LICENSE
MANIFEST.in
README.md
pandoc_latex_unlisted.py
setup.cfg
setup.py
pandoc_latex_unlisted.egg-info/PKG-INFO
pandoc_latex_unlisted.egg-info/SOURCES.txt
pandoc_latex_unlisted.egg-info/dependency_links.txt
pandoc_latex_unlisted.egg-info/entry_points.txt
pandoc_latex_unlisted.egg-info/requires.txt
pandoc_latex_unlisted.egg-info/top_level.txt