Metadata-Version: 2.1
Name: pandoc-latex-unlisted
Version: 0.2.0
Summary: A pandoc filter for unlisting some headers in the table of contents in LaTeX
Home-page: https://github.com/chdemko/pandoc-latex-unlisted
Author: Christophe Demko
Author-email: chdemko@gmail.com
Maintainer: Christophe Demko
Maintainer-email: chdemko@gmail.com
License: BSD-3-Clause
Download-URL: https://github.com/chdemko/pandoc-latex-unlisted/archive/master.zip
Keywords: pandoc filters latex unlisted
Platform: UNKNOWN
Classifier: Development Status :: 4 - Beta
Classifier: Operating System :: OS Independent
Classifier: Environment :: Console
Classifier: Intended Audience :: End Users/Desktop
Classifier: Intended Audience :: Developers
Classifier: Topic :: Software Development :: Build Tools
Classifier: Topic :: Software Development :: Documentation
Classifier: Topic :: Text Processing :: Filters
Classifier: Programming Language :: Python :: 2.7
Classifier: Programming Language :: Python :: 3.4
Classifier: Programming Language :: Python :: 3.5
Provides-Extra: test
Provides-Extra: dev
